EpidemicKabuLibrary/__init__.py
EpidemicKabuLibrary/kabu.py
EpidemicKabuLibrary/kabuPeaksValleys.py
EpidemicKabuLibrary/kabuWaves.py
KabuEpidemic-0.0.0.dist-info/METADATA
KabuEpidemic-0.0.0.dist-info/WHEEL
KabuEpidemic-0.0.0.dist-info/top_level.txt
KabuEpidemic-0.0.0.dist-info/RECORD
